[{"flavor": "watermelon"}, {"flavor": "orange"}, {"flavor": "raspberry"}, {"flavor": "watermelon"}, {"flavor": "raspberry"}, {"flavor": "raspberry"}, {"flavor": "cherry"}, {"flavor": "raspberry"}, {"flavor": "watermelon"}, {"flavor": "cherry"}, {"flavor": "orange"}, {"flavor": "orange"}, {"flavor": "orange"}, {"flavor": "orange"}, {"flavor": "cherry"}, {"flavor": "orange"}, {"flavor": "raspberry"}, {"flavor": "pineapple"}, {"flavor": "orange"}, {"flavor": "cherry"}, {"flavor": "cherry"}, {"flavor": "watermelon"}, {"flavor": "cherry"}, {"flavor": "cherry"}, {"flavor": "cherry"}, {"flavor": "raspberry"}, {"flavor": "raspberry"}, {"flavor": "raspberry"}, {"flavor": "cherry"}, {"flavor": "orange"}, {"flavor": "pineapple"}, {"flavor": "cherry"}, {"flavor": "watermelon"}, {"flavor": "pineapple"}, {"flavor": "pineapple"}, {"flavor": "raspberry"}, {"flavor": "raspberry"}, {"flavor": "watermelon"}, {"flavor": "raspberry"}, {"flavor": "cherry"}]